src/design/module_2bitcounter.sv
module module_2bitcounter( input  logic clk,
    input  logic rst,     // Reset asíncrono activo en bajo
    input  logic stop,        // Enable
    output logic [1:0] count );
    always_ff @(posedge clk , posedge rst) begin
        if (rst) begin
           count <= 2'b00; 
        end
        else if (!stop) begin
            count <= count + 1;
        end
    end
endmodule

src/sim/module_2bitcounter_tb.sv
`timescale 1ns/1ns

module module_2bitcounter_tb;
  // Inputs
  reg clk;
  reg rst;
  reg stop;
  // Outputs
  wire [1:0] count;

  // Instantiate the 2-bit counter Verilog code
  module_2bitcounter dut (
    .clk(clk), 
    .rst(rst), 
    .stop(stop),
    .count(count)
  );

  initial begin
    clk = 0;
    forever #10 clk = ~clk; // Clock generation with a period of 20 time units
  end

  initial begin
     $monitor( "At time %t, count = %b", $time, count);
    rst = 1; // Reset the system
    #5;      // Wait for a short time before releasing reset
    rst = 0; stop = 0; // Release reset
    #1000;    // Wait for some time to observe the counter behavior
    stop = 1; // Stop the counter
    #20;      // Wait for a short time
    $stop;   // Stop the simulation
  end
   initial begin
    $dumpfile("module_2bitcounter_tb.vcd");
    $dumpvars(0, module_2bitcounter_tb);
  end
  endmodule

src/build/module_2bitcounter_tb.vcd
$date
	Sat May 10 14:02:29 2025
$end
$version
	Icarus Verilog
$end
$timescale
	1ns
$end
$scope module module_2bitcounter_tb $end
$var wire 2 ! count [1:0] $end
$var reg 1 " clk $end
$var reg 1 # rst $end
$var reg 1 $ stop $end
$scope module dut $end
$var wire 1 " clk $end
$var wire 1 # rst $end
$var wire 1 $ stop $end
$var reg 2 % count [1:0] $end
$upscope $end
$upscope $end
$enddefinitions $end
$comment Show the parameter values. $end
$dumpall
$end
#0
$dumpvars
b0 %
x$
1#
0"
b0 !
$end
#5
0$
0#
#10
b1 !
b1 %
1"
#20
0"
#30
b10 !
b10 %
1"
#40
0"
#50
b11 !
b11 %
1"
#60
0"
#70
b0 !
b0 %
1"
#80
0"
#90
b1 !
b1 %
1"
#100
0"
#110
b10 !
b10 %
1"
#120
0"
#130
b11 !
b11 %
1"
#140
0"
#150
b0 !
b0 %
1"
#160
0"
#170
b1 !
b1 %
1"
#180
0"
#190
b10 !
b10 %
1"
#200
0"
#210
b11 !
b11 %
1"
#220
0"
#230
b0 !
b0 %
1"
#240
0"
#250
b1 !
b1 %
1"
#260
0"
#270
b10 !
b10 %
1"
#280
0"
#290
b11 !
b11 %
1"
#300
0"
#310
b0 !
b0 %
1"
#320
0"
#330
b1 !
b1 %
1"
#340
0"
#350
b10 !
b10 %
1"
#360
0"
#370
b11 !
b11 %
1"
#380
0"
#390
b0 !
b0 %
1"
#400
0"
#410
b1 !
b1 %
1"
#420
0"
#430
b10 !
b10 %
1"
#440
0"
#450
b11 !
b11 %
1"
#460
0"
#470
b0 !
b0 %
1"
#480
0"
#490
b1 !
b1 %
1"
#500
0"
#510
b10 !
b10 %
1"
#520
0"
#530
b11 !
b11 %
1"
#540
0"
#550
b0 !
b0 %
1"
#560
0"
#570
b1 !
b1 %
1"
#580
0"
#590
b10 !
b10 %
1"
#600
0"
#610
b11 !
b11 %
1"
#620
0"
#630
b0 !
b0 %
1"
#640
0"
#650
b1 !
b1 %
1"
#660
0"
#670
b10 !
b10 %
1"
#680
0"
#690
b11 !
b11 %
1"
#700
0"
#710
b0 !
b0 %
1"
#720
0"
#730
b1 !
b1 %
1"
#740
0"
#750
b10 !
b10 %
1"
#760
0"
#770
b11 !
b11 %
1"
#780
0"
#790
b0 !
b0 %
1"
#800
0"
#810
b1 !
b1 %
1"
#820
0"
#830
b10 !
b10 %
1"
#840
0"
#850
b11 !
b11 %
1"
#860
0"
#870
b0 !
b0 %
1"
#880
0"
#890
b1 !
b1 %
1"
#900
0"
#910
b10 !
b10 %
1"
#920
0"
#930
b11 !
b11 %
1"
#940
0"
#950
b0 !
b0 %
1"
#960
0"
#970
b1 !
b1 %
1"
#980
0"
#990
b10 !
b10 %
1"
#1000
0"
#1005
1$
