src/design/module_debouncer.sv
module module_debouncer(
    input  logic btn,
    input  logic clk,
    input  logic rst,
    output logic tecla, // pulso de un ciclo
    output logic stop   // misma señal
);

    // --- sincronizador de 2 etapas para el rebote ---
    logic n1, n2;
    dff dff1(.d(btn), .clk(clk), .rst(rst), .q(n1));
    dff dff2(.d(n1), .clk(clk), .rst(rst), .q(n2));

    // --- detecta que n1 y n2 son iguales (señal estable) ---
    logic n3;
    assign n3 = ~(n1 ^ n2);

    // --- contador para asegurarse de que la señal lleve X clocks estable ---
    logic n4;
    contador cont(
        .clk(clk),
        .rst(rst),
        .in (n3),
        .flg(n4)      // n4 = 1 sólo un ciclo cuando lleva 16 clocks estable
    );

    // --- pulso de un solo ciclo: cuando ya está estable y es alto ---
    assign tecla = n4 & n2;
    assign stop  = tecla;

endmodule


//-----------------------------------------------------------------------------
// Contador: flg = 1 durante 1 ciclo cuando `in` lleva 16 clocks estables
//-----------------------------------------------------------------------------
module contador(
    input  logic       clk,
    input  logic       rst,
    input  logic       in,
    output logic       flg
);
    logic [4:0] count;
    always_ff @ (posedge clk) begin
        if (!rst) begin
            count <= 5'd0;
            flg   <= 1'b0;
        end
        else if (in) begin
            // cuenta hasta 25, luego dispara flg y resetea
            if (count == 5'd25) begin
                count <= 5'd0;
                flg   <= 1'b1;
            end else begin
                count <= count + 1;
                flg   <= 1'b0;
            end
        end
        else begin
            count <= 5'd0;
            flg   <= 1'b0;
        end
    end
endmodule


//-----------------------------------------------------------------------------
// D flip-flop con reset síncrono
//-----------------------------------------------------------------------------
module dff(
    input  logic d,
    input  logic clk,
    input  logic rst,
    output logic q
);
    always_ff @ (posedge clk) begin
        if (!rst)   q <= 1'b0;
        else        q <= d;
    end
endmodule

src/sim/module_debouncer_tb.sv
`timescale 1ns / 1ns
// testbench verilog code for debouncing button without creating another clock
module module_debouncer_tb;
 // Inputs
 logic btn;
 logic clk;
 logic rst;
 // Outputs
 logic stop;
 logic tecla;
 // Instantiate the debouncing Verilog code
 module_debouncer dut (
  .btn(btn), 
  .clk(clk), 
  .rst(rst),
  .tecla(tecla),
  .stop(stop)
 );
 initial begin
  clk = 0;
 forever #10 clk = ~clk; // Clock generation with a period of 100 time units
 end
 initial begin
    rst = 1'b0; // Reset the system
  #10;
  rst = 1'b1;
  btn = 0;
  #10;
  btn=1;
  #20;
  btn = 0;
  #10;
  btn=1;
  #30; 
  btn = 0;
  #10;
  btn=1;
  #40;
  btn = 0;
  #10;
  btn=1;
  #30; 
  btn = 0;
  #10;
  btn=1; 
  #1000; 
  btn = 0;
  #10;
  btn=1;
  #20;
  btn = 0;
  #10;
  btn=1;
  #30; 
  btn = 0;
  #10;
  btn=1;
  #40;
  btn = 0; 
  #100;
  $finish; // End the simulation
 end 
 initial begin
    $dumpfile("module_debouncer_tb.vcd");
    $dumpvars(0, module_debouncer_tb);
end
      
endmodule

src/build/module_debouncer_tb.vcd
$date
	Fri May 16 20:25:27 2025
$end
$version
	Icarus Verilog
$end
$timescale
	1ns
$end
$scope module module_debouncer_tb $end
$var wire 1 ! tecla $end
$var wire 1 " stop $end
$var reg 1 # btn $end
$var reg 1 $ clk $end
$var reg 1 % rst $end
$scope module dut $end
$var wire 1 # btn $end
$var wire 1 $ clk $end
$var wire 1 & n3 $end
$var wire 1 % rst $end
$var wire 1 " stop $end
$var wire 1 ! tecla $end
$var wire 1 ' n4 $end
$var wire 1 ( n2 $end
$var wire 1 ) n1 $end
$scope module cont $end
$var wire 1 $ clk $end
$var wire 1 & in $end
$var wire 1 % rst $end
$var reg 5 * count [4:0] $end
$var reg 1 ' flg $end
$upscope $end
$scope module dff1 $end
$var wire 1 $ clk $end
$var wire 1 # d $end
$var wire 1 % rst $end
$var reg 1 ) q $end
$upscope $end
$scope module dff2 $end
$var wire 1 $ clk $end
$var wire 1 ) d $end
$var wire 1 % rst $end
$var reg 1 ( q $end
$upscope $end
$upscope $end
$upscope $end
$enddefinitions $end
$comment Show the parameter values. $end
$dumpall
$end
#0
$dumpvars
bx *
x)
x(
x'
x&
0%
0$
x#
x"
x!
$end
#10
0"
0!
0)
0'
b0 *
0#
1%
1$
#20
1#
0$
#30
0&
0(
1)
1$
#40
0$
0#
#50
1&
1(
1$
1#
#60
0$
#70
b1 *
1$
#80
0$
0#
#90
b10 *
1$
1#
#100
0$
#110
b11 *
1$
#120
0$
#130
0&
0)
b100 *
1$
0#
#140
0$
1#
#150
b0 *
0(
1)
1$
#160
0$
#170
0)
1(
1$
0#
#180
0$
1#
#190
0(
1)
1$
#200
0$
#210
1&
1(
1$
#220
0$
#230
b1 *
1$
#240
0$
#250
b10 *
1$
#260
0$
#270
b11 *
1$
#280
0$
#290
b100 *
1$
#300
0$
#310
b101 *
1$
#320
0$
#330
b110 *
1$
#340
0$
#350
b111 *
1$
#360
0$
#370
b1000 *
1$
#380
0$
#390
b1001 *
1$
#400
0$
#410
b1010 *
1$
#420
0$
#430
b1011 *
1$
#440
0$
#450
b1100 *
1$
#460
0$
#470
b1101 *
1$
#480
0$
#490
b1110 *
1$
#500
0$
#510
b1111 *
1$
#520
0$
#530
b10000 *
1$
#540
0$
#550
b10001 *
1$
#560
0$
#570
b10010 *
1$
#580
0$
#590
b10011 *
1$
#600
0$
#610
b10100 *
1$
#620
0$
#630
b10101 *
1$
#640
0$
#650
b10110 *
1$
#660
0$
#670
b10111 *
1$
#680
0$
#690
b11000 *
1$
#700
0$
#710
b11001 *
1$
#720
0$
#730
1"
1!
1'
b0 *
1$
#740
0$
#750
0"
0!
0'
b1 *
1$
#760
0$
#770
b10 *
1$
#780
0$
#790
b11 *
1$
#800
0$
#810
b100 *
1$
#820
0$
#830
b101 *
1$
#840
0$
#850
b110 *
1$
#860
0$
#870
b111 *
1$
#880
0$
#890
b1000 *
1$
#900
0$
#910
b1001 *
1$
#920
0$
#930
b1010 *
1$
#940
0$
#950
b1011 *
1$
#960
0$
#970
b1100 *
1$
#980
0$
#990
b1101 *
1$
#1000
0$
#1010
b1110 *
1$
#1020
0$
#1030
b1111 *
1$
#1040
0$
#1050
b10000 *
1$
#1060
0$
#1070
b10001 *
1$
#1080
0$
#1090
b10010 *
1$
#1100
0$
#1110
b10011 *
1$
#1120
0$
#1130
b10100 *
1$
#1140
0$
#1150
b10101 *
1$
#1160
0$
#1170
b10110 *
1$
#1180
0$
0#
#1190
b10111 *
1$
1#
#1200
0$
#1210
0&
0)
b11000 *
1$
0#
#1220
0$
1#
#1230
b0 *
0(
1)
1$
#1240
0$
#1250
0)
1(
1$
0#
#1260
0$
1#
#1270
0(
1)
1$
#1280
0$
#1290
1&
1(
1$
#1300
0$
0#
#1310
0&
b1 *
0)
1$
#1320
0$
#1330
1&
0(
b0 *
1$
#1340
0$
#1350
b1 *
1$
#1360
0$
#1370
b10 *
1$
#1380
0$
#1390
b11 *
1$
