src/design/module_deco_tecladohex.sv
/* Decode the asserted fila and col
                                    col[0] col[1] col[2] col[3]
        fila[0]                      1       2       3       A
        fila[1]                      4       5       6       B
        fila[2]                      7       8       9       C
        fila[3]                      *       0       #       D           */

module module_deco_tecladohex (
    input  logic [3:0] fila,      // one-hot, activo en alto
    input  logic [3:0] col,      // one-hot, activo en alto
    input  logic        tecla, // tecla presionada
    output logic [3:0] num, // número en binario natural
    output logic       rdy
);

    always_comb begin
        if (tecla == 0) begin
            num = 4'b0000;
            rdy = 0; // No hay tecla presionada
        end
        else if (tecla == 1) begin
        rdy = 1'b1;
        case ({fila, col})
            8'b0001_0001: num = 4'b0001;     // 1-fila[0], col[0]
            8'b0001_0010: num = 4'b0010;    // 2
            8'b0001_0100: num = 4'b0011;   // 3
            8'b0001_1000: num = 4'b1010;  // A

            8'b0010_0001: num = 4'b0100;     // 4-fila[1], col[0]
            8'b0010_0010: num = 4'b0101;    // 5
            8'b0010_0100: num = 4'b0110;   // 6
            8'b0010_1000: num = 4'b1011;  // B

            8'b0100_0001: num = 4'b0111;     // 7-fila[2], col[0]
            8'b0100_0010: num = 4'b1000;    // 8
            8'b0100_0100: num = 4'b1001;   // 9
            8'b0100_1000: num = 4'b1100;  // C

            8'b1000_0001: num = 4'b1110;     // * - fila[3], col[0]
            8'b1000_0010: num = 4'b0000;    // 0
            8'b1000_0100: num = 4'b1111;   // # - fila[3], col[2]
            8'b1000_1000: num = 4'b1101;  // D

            default: begin
                num = 4'b0000;
                rdy = 0;
            end
        endcase
        end
    end
endmodule

src/sim/module_deco_tecladohex_tb.sv
`timescale 1ns/1ns

module module_deco_tecladohex_tb;
    // Inputs
    reg [3:0] fila;
    reg [3:0] col;
    reg tecla;

    // Outputs
    wire [3:0] num;
    wire rdy;

    // Instantiate the module under test
    module_deco_tecladohex uut (
        .fila(fila),
        .col(col),
        .tecla(tecla),
        .num(num),
        .rdy(rdy)
    );

    initial begin
        // Monitor the outputs
        $monitor("Time: %0t | fila: %b | col: %b | tecla: %b | num: %b | rdy: %b", 
                 $time, fila, col, tecla, num, rdy);
        // Initialize inputs
        fila = 4'b0000;
        col = 4'b0000;
        tecla = 1'b0;
        #10;
        // Test case 1: Tecla 1
        fila = 4'b0001; col = 4'b0001; tecla = 1;
        #10;
        // Test case 2: Tecla 2
        fila = 4'b0001; col = 4'b0010; tecla = 1;
        #10;
        // Test case 3: Tecla 3
        fila = 4'b0001; col = 4'b0100; tecla = 1;
        #10;
        // Test case 4: Tecla A
        fila = 4'b0001; col = 4'b1000; tecla = 1;
        #10;
        // Test case 5: Tecla 4
        fila = 4'b0010; col = 4'b0001; tecla = 1;
        #10;
        // Test case 6: Tecla 5
        fila = 4'b0010; col = 4'b0010; tecla = 1;
        #10;
        // Test case 7: Tecla 6
        fila = 4'b0010; col = 4'b0100; tecla = 1;
        #10;
        // Test case 8: Tecla B
        fila = 4'b0010; col = 4'b1000; tecla = 1;
        #10;
        // Test case 9: Tecla 7
        fila = 4'b0100; col = 4'b0001; tecla = 1;
        #10;
        // Test case 10: Tecla 8
        fila = 4'b0100; col = 4'b0010; tecla = 1;
        #10;
        // Test case 11: Tecla 9
        fila = 4'b0100; col = 4'b0100; tecla = 1;
        #10;
        // Test case 12: Tecla C
        fila = 4'b0100; col = 4'b1000; tecla = 1;
        #10;
        // Test case 13: Tecla *
        fila = 4'b1000; col = 4'b0001; tecla = 1;
        #10;
        // Test case 14: Tecla 0
        fila = 4'b1000; col = 4'b0010; tecla = 1;
        #10;
        // Test case 15: Tecla #
        fila = 4'b1000; col = 4'b0100; tecla = 1;
        #10;
        // Test case 16: Tecla D
        fila = 4'b1000; col = 4'b1000; tecla = 1;
        #10;
        // Test case 17: No tecla pressed
        fila = 4'b0000; col = 4'b0000; tecla = 0;
        #10;
        // Test case 18: Invalid input
        fila = 4'b0001; col = 4'b0000; tecla = 1;
        #10;
        // Test case 19: Invalid input
        fila = 4'b0001; col = 4'b0001; tecla = 0;
        #10;
        // Test case 20: Invalid input
        fila = 4'b0000; col = 4'b0010; tecla = 1;
        #10;
        $finish;
    end
   initial begin
    $dumpfile("module_deco_tecladohex_tb.vcd");
    $dumpvars(0, module_deco_tecladohex_tb);
end

endmodule

src/build/module_deco_tecladohex_tb.vcd
$date
	Sat May 10 16:54:22 2025
$end
$version
	Icarus Verilog
$end
$timescale
	1ns
$end
$scope module module_deco_tecladohex_tb $end
$var wire 1 ! rdy $end
$var wire 4 " num [3:0] $end
$var reg 4 # col [3:0] $end
$var reg 4 $ fila [3:0] $end
$var reg 1 % tecla $end
$scope module uut $end
$var wire 4 & col [3:0] $end
$var wire 4 ' fila [3:0] $end
$var wire 1 % tecla $end
$var reg 4 ( num [3:0] $end
$var reg 1 ! rdy $end
$upscope $end
$upscope $end
$enddefinitions $end
$comment Show the parameter values. $end
$dumpall
$end
#0
$dumpvars
b0 (
b0 '
b0 &
0%
b0 $
b0 #
b0 "
0!
$end
#10
b1 "
b1 (
1!
1%
b1 #
b1 &
b1 $
b1 '
#20
b10 "
b10 (
b10 #
b10 &
#30
b11 "
b11 (
b100 #
b100 &
#40
b1010 "
b1010 (
b1000 #
b1000 &
#50
b100 "
b100 (
b1 #
b1 &
b10 $
b10 '
#60
b101 "
b101 (
b10 #
b10 &
#70
b110 "
b110 (
b100 #
b100 &
#80
b1011 "
b1011 (
b1000 #
b1000 &
#90
b111 "
b111 (
b1 #
b1 &
b100 $
b100 '
#100
b1000 "
b1000 (
b10 #
b10 &
#110
b1001 "
b1001 (
b100 #
b100 &
#120
b1100 "
b1100 (
b1000 #
b1000 &
#130
b1110 "
b1110 (
b1 #
b1 &
b1000 $
b1000 '
#140
b0 "
b0 (
b10 #
b10 &
#150
b1111 "
b1111 (
b100 #
b100 &
#160
b1101 "
b1101 (
b1000 #
b1000 &
#170
0!
b0 "
b0 (
0%
b0 #
b0 &
b0 $
b0 '
#180
0!
1%
b1 $
b1 '
#190
0%
b1 #
b1 &
#200
0!
1%
b10 #
b10 &
b0 $
b0 '
